{
  "task_id": "website-4366",
  "repo": "asyncapi/website",
  "worker": "worker-04",
  "status": "completed",
  "sess_id": "sess-20260418031929-6c2f26cbf63e4142bfa45b685ea045a1",
  "expected_result_used": false,
  "duration_seconds": 900,
  "timestamp": "2026-04-17T12:35:00-07:00",
  "mano_cua": {
    "status": "STOPPED_BY_USER",
    "total_steps": 60,
    "last_action": "wait",
    "result": "unclear",
    "result_summary": "Next.js 15首次编译过慢，页面持续30分钟加载空白，无法到达Newsletter订阅功能。60步中大部分在等待页面加载。",
    "last_reasoning": "页面持续加载中（标签页图标旋转），内容区域完全空白，等待超过30分钟仍未完成首次编译。"
  }
}
