{
  "task_id": "automa-1316",
  "repo": "AutomaApp/automa",
  "worker": "worker-08",
  "status": "failed",
  "expected_result_used": false,
  "sess_id": null,
  "duration_seconds": 0,
  "timestamp": "2026-04-23T19:40:00+08:00",
  "mano_cua": null,
  "failure": {
    "type": "deploy_failed",
    "symptom": "fuse_repo_blocked",
    "attempted": ["fuse_trigger: automa-1051 (commit f0dca88858), automa-504 (commit 123fc29bf7)"],
    "recommendation": "同 repo 已有 2 个不同 buggy_commit deploy_failed，repo 级熔断"
  }
}
