{
  "task_id": "Armoria-pr206",
  "repo": "Azgaar/armoria",
  "worker": "worker-07",
  "status": "completed",
  "sess_id": "sess-20260423234138-438b0c194d3d4d6fa5978f7a57fe3a58",
  "expected_result_used": true,
  "duration_seconds": 902,
  "timestamp": "2026-04-23T08:56:00-07:00",
  "mano_cua": {
    "status": "STOPPED_BY_USER",
    "total_steps": 131,
    "last_action": "timeout_stop",
    "result": "abnormal",
    "result_summary": "发现 UX Bug：折叠区域收起时的 layout shift + 滚动调整导致意外点击。展开状态下按钮所在位置在折叠后因内容消失和页面自动滚动，变成其他元素的位置，快速点击可能触发非预期操作。使用 DevTools 移动端模拟和 CSS 检查确认折叠机制为自定义实现（非 HTML details/summary），但未能在有限步骤内确认 pointer-events 是否正确设置为 none。硬超时终止。",
    "last_reasoning": "Confirmed UX bug where fast collapse of section with scroll adjustment causes unintended clicks on other elements. When section collapses: page auto-scrolls, new content appears at positions where hidden buttons were, clicking where a hidden button was now hits a different button due to layout shift. Custom collapse implementation (not native details/summary). Timeout before fully verifying CSS pointer-events property."
  }
}
