{
  "task_id": "drawnix-pr318",
  "repo": "plait-board/drawnix",
  "worker": "worker-04",
  "status": "completed",
  "sess_id": "sess-20260422184930-ec1cb4ed35224015b36f09dc152c4d1a",
  "expected_result_used": true,
  "duration_seconds": 928,
  "timestamp": "2026-04-22T19:05:00+08:00",
  "mano_cua": {
    "status": "STOPPED_BY_USER",
    "total_steps": null,
    "last_action": null,
    "result": "unclear",
    "result_summary": "mano-cua花费大量步骤尝试测试缩放控件的百分比显示、tooltip和not-allowed光标，但受Chrome右键菜单干扰，未能完整验证所有三个测试点。缩放百分比显示可见（60%→70%），但tooltip和not-allowed光标测试未在捕获的输出中给出明确结论。",
    "last_reasoning": "mano-cua尝试通过点击缩放按钮测试zoom功能，发现点击缩放按钮时Chrome右键菜单意外弹出（可能是macOS Ctrl+click映射问题），后尝试用Ctrl+scroll方式缩放到最大值以测试not-allowed光标，但在到达极限值前任务结束。"
  },
  "note": "Terminal scrollback buffer限制，仅捕获到末尾分析文本。耗时较长(928s)，接近硬超时"
}
