{
  "task_id": "react-slick-1881",
  "repo": "akiran/react-slick",
  "worker": "worker-02",
  "status": "completed",
  "sess_id": "sess-20260427220631-0d2d21ca539d4da983f0641d8c0bb9ee",
  "expected_result_used": true,
  "duration_seconds": 360,
  "timestamp": "2026-04-27T22:13:00+08:00",
  "mano_cua": {
    "status": "COMPLETED",
    "total_steps": 26,
    "last_action": "DONE",
    "result": "abnormal",
    "result_summary": "确认bug：Fade轮播（fade=true, infinite=false）箭头按钮从第2张起完全失效。next按钮只能从第1张→第2张，之后点击完全无反应。previous按钮在任何非第1张位置都无反应。dots导航正常工作。测试多次重复确认bug一致复现。",
    "last_reasoning": "从第1张点击next成功到第2张，再次点击next/previous完全无反应。通过dots跳到第3/4张后箭头也失效。bug一致可重复。"
  }
}
