{
  "task_id": "svelteui-202",
  "repo": "svelteuidev/svelteui",
  "worker": "worker-02",
  "status": "completed",
  "sess_id": "sess-20260416184309-04a7ddb5c5394ea580cc72a0887a4634",
  "expected_result_used": true,
  "duration_seconds": 420,
  "timestamp": "2026-04-16T18:50:00+08:00",
  "mano_cua": {
    "status": "COMPLETED",
    "total_steps": 26,
    "last_action": "DONE",
    "result": "abnormal",
    "result_summary": "Modal弹窗无法打开，点击Open Modal按钮后无任何弹窗显示，控制台报错Uncaught Error: Wrap your app in the SvelteUIProvider，Modal组件找不到SvelteUIProvider上下文导致功能完全失效",
    "last_reasoning": "Clicked Open Modal button twice, Modal popup never appeared. Console shows error: Uncaught (in promise) Error: Wrap your app in the SvelteUIProvider, or provide a sufficent target throught the target prop (Modal.svelte:41:15). The Modal component cannot find SvelteUIProvider context in the documentation site, causing Modal to fail completely. Additionally, the code example shows Modal content is just HTML comment <!-- Modal Content -->."
  }
}
