{
  "task_id": "docus-140",
  "repo": "nuxt-content/docus",
  "worker": "worker-07",
  "status": "failed",
  "sess_id": "sess-20260423172039-221c962ce7eb454b91fe7f36ae243502",
  "expected_result_used": true,
  "duration_seconds": 904,
  "timestamp": "2026-04-23T02:35:00-07:00",
  "mano_cua": null,
  "failure": {
    "type": "timeout",
    "symptom": "硬超时 15 分钟，mano-cua 执行 52 步仍未完成。在分析桌面端和移动端布局间距时陷入过于详细的像素级分析",
    "attempted": [
      "mano-cua 正常启动并执行到 step 52",
      "已观察到部分结果：移动端 header 和 heading 之间有 75px 异常空白",
      "15 分钟硬超时后 mano-cua stop 终止"
    ],
    "recommendation": "任务描述涉及多个视口切换和间距检查，mano-cua 容易陷入过度分析"
  }
}
