{
  "app_name": "Composition Api",
  "buggy_commit": "b1b767377d",
  "deploy_commands": [
    "git clone https://github.com/nuxt-community/composition-api.git composition-api-64",
    "cd composition-api-64",
    "git checkout b1b767377d",
    "npm install",
    "npm run dev"
  ],
  "deploy_verify": "curl -s http://localhost:3000 | grep -q '<'",
  "dev_url": "http://localhost:3000",
  "expected_result_zh": "页面正常渲染，layout 组件中通过 useMeta() 设置的 head 信息（如页面标题）正确生效，控制台无 '[vue-composition-api] must call Vue.use(plugin) before using any function' 错误。",
  "fix_commit": "6c8f46f14a",
  "framework": "nuxt",
  "repo": "nuxt-community/composition-api",
  "repo_size_kb": 8270,
  "task_id": "composition-api-64",
  "test_description_zh": "在 Nuxt 项目的 layout 组件中使用 useMeta() 组合式 API 设置页面 head 信息（如 title），然后访问使用该 layout 的页面，观察页面是否正常渲染以及控制台是否出现报错。",
  "test_page": "/",
  "pr_number": 792,
  "timeout_minutes": 10,
  "issue_number": 64,
  "max_steps": 80
}