{
  "app_name": "Ever Gauzy",
  "buggy_commit": "1bcee94793",
  "deploy_commands": [
    "git clone https://github.com/ever-co/ever-gauzy.git ever-gauzy-9650",
    "cd ever-gauzy-9650",
    "git checkout 1bcee94793",
    "npm install",
    "npm run dev"
  ],
  "deploy_verify": "curl -s http://localhost:4200 | grep -q '<'",
  "dev_url": "http://localhost:4200",
  "expected_result_zh": "帮助中心文章的描述字段在保存后能够正确持久化，重新打开文章时描述字段应正确回显之前保存的内容；修改描述后再次保存，更新的描述内容也应正确显示，不会出现数据丢失或显示为空的情况。",
  "fix_commit": "dd11119053",
  "framework": "angular",
  "repo": "ever-co/ever-gauzy",
  "repo_size_kb": 232632,
  "task_id": "ever-gauzy-pr9650",
  "test_description_zh": "进入帮助中心模块，创建或编辑一篇文章，在文章描述字段中输入内容并保存。然后重新打开该文章，观察描述字段是否正确回显之前保存的内容。再次修改描述字段内容并保存，验证更新后的内容是否正确保存和回显。",
  "test_page": "/",
  "pr_number": 9650,
  "timeout_minutes": 10,
  "issue_number": 9650,
  "max_steps": 80
}