{
  "app_name": "Ext Saladict",
  "buggy_commit": "ad2ab1ecf9",
  "deploy_commands": [
    "git clone https://github.com/crimx/ext-saladict.git ext-saladict-298",
    "cd ext-saladict-298",
    "git checkout ad2ab1ecf9",
    "npm install",
    "npm run dev"
  ],
  "deploy_verify": "curl -s http://localhost:3000 | grep -q '<'",
  "dev_url": "http://localhost:3000",
  "expected_result_zh": "划词翻译面板弹出后，浏览器标签页上的网页标题应保持为原网页的标题，不应被修改为 'Saladict Panel' 或其他非原始标题的内容。",
  "fix_commit": "bae69df702",
  "framework": "react",
  "repo": "crimx/ext-saladict",
  "repo_size_kb": 16076,
  "task_id": "ext-saladict-298",
  "test_description_zh": "在任意网页上选中一段文字触发划词翻译功能，观察浏览器标签页上的网页标题是否发生变化。",
  "test_page": "/",
  "pr_number": 36,
  "timeout_minutes": 10,
  "issue_number": 298,
  "max_steps": 80
}