{
  "app_name": "Formbuilder",
  "buggy_commit": "28e1236b69",
  "deploy_commands": [
    "git clone https://github.com/kevinchappell/formBuilder.git formBuilder-1484",
    "cd formBuilder-1484",
    "git checkout 28e1236b69",
    "npm install",
    "npm run dev"
  ],
  "deploy_verify": "curl -s http://localhost:5173 | grep -q '<'",
  "dev_url": "http://localhost:5173",
  "expected_result_zh": "Text Area 控件的设置面板中不应出现 'Type'（subtype）下拉选择字段，该属性已被 disabledAttrs 配置成功禁用隐藏。",
  "fix_commit": "763378c76f",
  "framework": "other",
  "repo": "kevinchappell/formBuilder",
  "repo_size_kb": 26663,
  "task_id": "formBuilder-1484",
  "test_description_zh": "在 formBuilder 中配置 disabledAttrs 包含 'subtype'，然后拖拽一个 Text Area 控件到表单中，点击该控件展开其设置面板，观察设置面板中是否还显示 'Type'（subtype）字段。",
  "test_page": "/",
  "pr_number": 1486,
  "timeout_minutes": 10,
  "issue_number": 1484,
  "max_steps": 80
}