{
  "app_name": "Gridsheet",
  "buggy_commit": "cf2cce26de",
  "deploy_commands": [
    "git clone https://github.com/walkframe/gridsheet.git gridsheet-56",
    "cd gridsheet-56",
    "git checkout cf2cce26de",
    "npm install",
    "npm run dev"
  ],
  "deploy_verify": "curl -s http://localhost:3000 | grep -q '<'",
  "dev_url": "http://localhost:3000",
  "expected_result_zh": "FormulaBar 应正确显示和处理包含换行符的文本内容，换行能够正常渲染，编辑时多行文本的显示与输入保持一致，不会出现换行丢失、文本错位或显示异常的问题。",
  "fix_commit": "67c6b3c42c",
  "framework": "react",
  "repo": "walkframe/gridsheet",
  "repo_size_kb": 5326,
  "task_id": "gridsheet-pr56",
  "test_description_zh": "在 gridsheet 的 Storybook 中打开包含 FormulaBar 的示例页面，选中一个单元格并在 FormulaBar 中输入包含换行符的多行文本（例如通过粘贴或 Shift+Enter），观察 FormulaBar 对换行内容的显示和编辑行为。",
  "test_page": "/",
  "pr_number": 56,
  "timeout_minutes": 10,
  "issue_number": 56,
  "max_steps": 80
}