{
  "app_name": "Gridsheet",
  "buggy_commit": "9e52564c9b",
  "deploy_commands": [
    "git clone https://github.com/walkframe/gridsheet.git gridsheet-67",
    "cd gridsheet-67",
    "git checkout 9e52564c9b",
    "npm install",
    "npm run dev"
  ],
  "deploy_verify": "curl -s http://localhost:3000 | grep -q '<'",
  "dev_url": "http://localhost:3000",
  "expected_result_zh": "1. 所有单元格应精确对齐，没有细微的错位现象，边框和内容排列整齐一致。\n2. 自动填充操作完成后，焦点应正确保留在填充区域或最后操作的单元格上，不应丢失焦点。\n3. 包含百分号(%)的公式应被正确解析，例如 =A1*50% 应等价于 =A1*0.5，并显示正确的计算结果。\n4. 表格的最大宽度不应超过其外部容器元素的宽度，内容应在容器范围内正确显示。",
  "fix_commit": "8308469d1b",
  "framework": "react",
  "repo": "walkframe/gridsheet",
  "repo_size_kb": 5326,
  "task_id": "gridsheet-pr67",
  "test_description_zh": "1. 打开 gridsheet 页面，观察单元格的对齐情况，检查单元格边框和内容是否整齐排列。\n2. 选中一个单元格区域，使用自动填充（拖拽填充手柄）向下或向右填充数据，完成后观察焦点状态。\n3. 在单元格中输入包含百分号(%)的公式（如 =A1*50%），确认公式能正确解析和计算。\n4. 调整外部容器大小或在较窄的容器中加载 gridsheet，观察表格是否超出外部元素的边界。",
  "test_page": "/",
  "pr_number": 67,
  "timeout_minutes": 10,
  "issue_number": 67,
  "max_steps": 80
}