{
  "app_name": "Hyperdx",
  "buggy_commit": "20e4720761",
  "deploy_commands": [
    "git clone https://github.com/hyperdxio/hyperdx.git hyperdx-2038",
    "cd hyperdx-2038",
    "git checkout 20e4720761",
    "npm install",
    "npm run dev"
  ],
  "deploy_verify": "curl -s http://localhost:3000 | grep -q '<'",
  "dev_url": "http://localhost:3000",
  "expected_result_zh": "当过滤条件的值包含特殊SQL关键字（如 AND、OR）、运算符或转义引号时，过滤器标签应正确显示在搜索栏中，不会被静默隐藏或丢失，用户能正常看到并操作这些过滤条件。",
  "fix_commit": "76323dae35",
  "framework": "react",
  "repo": "hyperdxio/hyperdx",
  "repo_size_kb": 37031,
  "task_id": "hyperdx-pr2038",
  "test_description_zh": "在搜索页面中，添加一个过滤条件，其值包含特殊字符或SQL关键字（例如包含 AND、OR、转义引号等的单引号字符串，如 'value with AND keyword' 或 'it\\'s a test'），观察过滤器标签是否正常显示在搜索栏中。",
  "test_page": "/",
  "pr_number": 2038,
  "timeout_minutes": 10,
  "issue_number": 2038,
  "max_steps": 80
}