{
  "app_name": "Insforge",
  "buggy_commit": "cb8a96f6ca",
  "deploy_commands": [
    "git clone https://github.com/InsForge/InsForge.git InsForge-968",
    "cd InsForge-968",
    "git checkout cb8a96f6ca",
    "npm install",
    "npm run dev"
  ],
  "deploy_verify": "curl -s http://localhost:3000 | grep -q '<'",
  "dev_url": "http://localhost:3000",
  "expected_result_zh": "'Getting Started' 面板中的 'Step 2 - Verify Connection' 部分完整可见，或当内容超出面板可视区域时面板可正常滚动，用户能够查看并访问所有步骤的内容。",
  "fix_commit": "de288c0ed7",
  "framework": "react",
  "repo": "InsForge/InsForge",
  "repo_size_kb": 97456,
  "task_id": "InsForge-968",
  "test_description_zh": "打开项目 Dashboard 页面，查看 'Getting Started' 面板，确认 'Step 2 - Verify Connection' 部分是否可见，若面板内容超出可视区域，尝试滚动面板查看完整内容。",
  "test_page": "/",
  "pr_number": 1047,
  "timeout_minutes": 10,
  "issue_number": 968,
  "max_steps": 80
}