{
  "app_name": "Jest Preview",
  "buggy_commit": "9bd1145ae2",
  "deploy_commands": [
    "git clone https://github.com/nvh95/jest-preview.git jest-preview-138",
    "cd jest-preview-138",
    "git checkout 9bd1145ae2",
    "npm install",
    "npm run dev"
  ],
  "deploy_verify": "curl -s http://localhost:3000 | grep -q '<'",
  "dev_url": "http://localhost:3000",
  "expected_result_zh": "预览页面应正确渲染测试组件的 UI 快照内容，而不是显示 'No preview found. Please run: preview.debug();' 的错误提示信息。",
  "fix_commit": "fc1c7f9e08",
  "framework": "react",
  "repo": "nvh95/jest-preview",
  "repo_size_kb": 11221,
  "task_id": "jest-preview-138",
  "test_description_zh": "在 Linux 环境下，启动 jest-preview 示例项目，运行 `npm run test` 后打开浏览器访问预览页面，观察页面是否正确显示测试组件的预览内容。",
  "test_page": "/",
  "pr_number": 200,
  "timeout_minutes": 10,
  "issue_number": 138,
  "max_steps": 80
}