{
  "app_name": "Mud",
  "buggy_commit": "0e714cf3a7",
  "deploy_commands": [
    "git clone https://github.com/latticexyz/mud.git mud-3769",
    "cd mud-3769",
    "git checkout 0e714cf3a7",
    "npm install",
    "npm run dev"
  ],
  "deploy_verify": "curl -s http://localhost:3000 | grep -q '<'",
  "dev_url": "http://localhost:3000",
  "expected_result_zh": "页面加载完成后，ConnectKit 钱包连接模态框不应自动弹出，只有在用户主动点击连接按钮时才应显示该模态框",
  "fix_commit": "5b0ec82a03",
  "framework": "react",
  "repo": "latticexyz/mud",
  "repo_size_kb": 71498,
  "task_id": "mud-pr3769",
  "test_description_zh": "打开应用首页，观察页面加载完成后是否有钱包连接模态框（ConnectKit modal）自动弹出",
  "test_page": "/",
  "pr_number": 3769,
  "timeout_minutes": 10,
  "issue_number": 3769,
  "max_steps": 80
}