{
  "app_name": "Nuxt Directus",
  "buggy_commit": "1397152f70",
  "deploy_commands": [
    "git clone https://github.com/Intevel/nuxt-directus.git nuxt-directus-144",
    "cd nuxt-directus-144",
    "git checkout 1397152f70",
    "npm install",
    "npm run dev"
  ],
  "deploy_verify": "curl -s http://localhost:3000 | grep -q '<'",
  "dev_url": "http://localhost:3000",
  "expected_result_zh": "getThumbnail 方法应返回有效的缩略图 URL，图片元素能正常加载并显示对应的缩略图，不会抛出 'TypeError: Failed to construct URL: Invalid URL' 错误。",
  "fix_commit": "db425784fd",
  "framework": "nuxt",
  "repo": "Intevel/nuxt-directus",
  "repo_size_kb": 4104,
  "task_id": "nuxt-directus-144",
  "test_description_zh": "在页面中调用 getThumbnail 方法获取 Directus 资源的缩略图 URL，并将其作为图片 src 属性渲染到页面上，观察图片是否能正常显示。",
  "test_page": "/",
  "pr_number": 155,
  "timeout_minutes": 10,
  "issue_number": 144,
  "max_steps": 80
}