{
  "app_name": "Raneto",
  "buggy_commit": "8d0d52ddb5",
  "deploy_commands": [
    "git clone https://github.com/ryanlelek/Raneto.git Raneto-96",
    "cd Raneto-96",
    "git checkout 8d0d52ddb5",
    "npm install",
    "npm run dev"
  ],
  "deploy_verify": "curl -s http://localhost:5173 | grep -q '<'",
  "dev_url": "http://localhost:5173",
  "expected_result_zh": "当身份验证功能关闭且允许编辑功能开启时，用户无需登录即可在页面上看到编辑按钮，并能正常进入编辑模式对页面内容进行编辑。",
  "fix_commit": "af617e5347",
  "framework": "other",
  "repo": "ryanlelek/Raneto",
  "repo_size_kb": 4791,
  "task_id": "Raneto-96",
  "test_description_zh": "在未启用身份验证（authentication 设置为 false）但启用了允许编辑（allow_editing 设置为 true）的配置下，访问一个已有的文档页面，观察页面上是否出现编辑按钮/编辑入口。",
  "test_page": "/",
  "pr_number": 105,
  "timeout_minutes": 10,
  "issue_number": 96,
  "max_steps": 80
}