{
  "app_name": "React Slick",
  "buggy_commit": "313dac71de",
  "deploy_commands": [
    "git clone https://github.com/akiran/react-slick.git react-slick-1881",
    "cd react-slick-1881",
    "git checkout 313dac71de",
    "npm install",
    "npm run dev"
  ],
  "deploy_verify": "curl -s http://localhost:3000 | grep -q '<'",
  "dev_url": "http://localhost:3000",
  "expected_result_zh": "在 fade 为 true 且 infinite 为 false 的配置下，点击 next 按钮应能从第一张幻灯片依次切换到最后一张幻灯片，点击 previous 按钮应能从当前幻灯片依次切换回第一张幻灯片，所有幻灯片之间的切换均正常响应，不会出现点击无反应或卡住的情况。",
  "fix_commit": "3449f51490",
  "framework": "react",
  "repo": "akiran/react-slick",
  "repo_size_kb": 2330,
  "task_id": "react-slick-1881",
  "test_description_zh": "创建一个 react-slick 轮播组件，设置 fade 为 true 且 infinite 为 false。点击下一张（next）按钮，依次浏览所有幻灯片，然后点击上一张（previous）按钮，依次返回浏览所有幻灯片。观察每次点击是否都能正常切换幻灯片。",
  "test_page": "/",
  "pr_number": 1890,
  "timeout_minutes": 10,
  "issue_number": 1881,
  "max_steps": 80
}