{
  "task_id": "react-grid-layout-918",
  "repo": "react-grid-layout/react-grid-layout",
  "issue_number": 918,
  "pr_number": 2059,
  "buggy_commit": "9129bee43d",
  "fix_commit": "915613d54b",
  "framework": "unknown",
  "deploy_commands": [
    "git clone https://github.com/react-grid-layout/react-grid-layout.git",
    "cd react-grid-layout",
    "git checkout 9129bee43d",
    "npm install",
    "npm run dev"
  ],
  "deploy_verify": "curl -s http://localhost:3000 | grep -q '<'",
  "dev_url": "http://localhost:3000",
  "test_page": "/",
  "app_name": "react-grid-layout",
  "test_description_zh": "测试 react-grid-layout 在 margin 和 containerPadding 设置为不同值时的拖拽功能。具体步骤：1. 打开页面，找到网格布局的演示区域。2. 如果页面有多个示例或配置选项，尝试找到可以设置 margin 和 containerPadding 的地方，将它们设置为不同的值（例如 margin 为 [10, 10]，containerPadding 为 [30, 30]）。3. 拖拽一个网格项目（GridItem），观察拖拽过程中占位符（placeholder）的位置是否与被拖拽的网格项目位置保持一致、紧密跟随。4. 将网格项目拖拽到不同位置并释放，确认项目最终放置的位置与拖拽时预期的目标位置一致。5. 多次拖拽不同的网格项目，验证占位符始终准确显示在鼠标拖拽对应的网格位置上。始终在浏览器内操作，禁止打开 Terminal 或其他应用程序。如果在浏览器中找不到目标功能，直接报告 unclear。",
  "expected_result_zh": "当 margin 和 containerPadding 设置为不同值时，拖拽网格项目过程中，占位符（placeholder）应紧密跟随被拖拽的项目，两者位置保持一致，不应出现占位符明显偏离拖拽项目的情况。释放后项目应落在正确的网格位置。",
  "max_steps": 80,
  "timeout_minutes": 15
}
