{
  "app_name": "Rx Player",
  "buggy_commit": "bce7633c39",
  "deploy_commands": [
    "git clone https://github.com/canalplus/rx-player.git rx-player-1502",
    "cd rx-player-1502",
    "git checkout bce7633c39",
    "npm install",
    "npm run dev"
  ],
  "deploy_verify": "curl -s http://localhost:5173 | grep -q '<'",
  "dev_url": "http://localhost:5173",
  "expected_result_zh": "播放器在播放多 Period 内容时，应用能够正确识别当前正在播放的 Period，并能正常展示该 Period 对应的音频轨道列表和文本（字幕）轨道列表供用户选择。",
  "fix_commit": "9652f84259",
  "framework": "other",
  "repo": "canalplus/rx-player",
  "repo_size_kb": 157241,
  "task_id": "rx-player-1502",
  "test_description_zh": "在播放器中播放包含多个 Period 的多时段内容（如 DASH 多 Period 流），观察播放过程中是否能正确获取当前正在播放的 Period 信息，并验证应用是否能据此展示当前 Period 对应的音轨和字幕轨道列表。",
  "test_page": "/",
  "pr_number": 1534,
  "timeout_minutes": 10,
  "issue_number": 1502,
  "max_steps": 80
}