{
  "app_name": "Slate Angular",
  "buggy_commit": "4ef6370b65",
  "deploy_commands": [
    "git clone https://github.com/worktile/slate-angular.git slate-angular-244",
    "cd slate-angular-244",
    "git checkout 4ef6370b65",
    "npm install",
    "npm run dev"
  ],
  "deploy_verify": "curl -s http://localhost:4200 | grep -q '<'",
  "dev_url": "http://localhost:4200",
  "expected_result_zh": "三击后，整个段落的所有内容（包括普通文本和 void 元素）应被完整选中，选区应覆盖段落中的所有元素，与标准文本编辑器的三击全选段落行为一致。",
  "fix_commit": "fa01d81fbf",
  "framework": "angular",
  "repo": "worktile/slate-angular",
  "repo_size_kb": 4218,
  "task_id": "slate-angular-244",
  "test_description_zh": "在编辑器中创建一个包含 void 元素（如图片、分割线等）的段落，段落中同时包含普通文本内容。使用鼠标在该段落的文本区域进行三击操作，观察段落内容的选中情况。",
  "test_page": "/",
  "pr_number": 253,
  "timeout_minutes": 10,
  "issue_number": 244,
  "max_steps": 80
}