{
  "task_id": "sorry-cypress-310",
  "repo": "sorry-cypress/sorry-cypress",
  "issue_number": 310,
  "pr_number": 313,
  "buggy_commit": "561d347a83",
  "fix_commit": "b8da8d4236",
  "framework": "unknown",
  "deploy_commands": [
    "git clone https://github.com/sorry-cypress/sorry-cypress.git",
    "cd sorry-cypress",
    "git checkout 561d347a83",
    "yarn install",
    "npm run dev"
  ],
  "deploy_verify": "curl -s http://localhost:3000 | grep -q '<'",
  "dev_url": "http://localhost:3000",
  "test_page": "/",
  "app_name": "sorry-cypress",
  "test_description_zh": "测试 sorry-cypress Dashboard 中项目的运行记录列表展示功能。步骤：1. 在浏览器中打开 Dashboard 首页；2. 查看是否有已存在的项目列表，如果有项目则点击进入某个项目；3. 在项目详情页中查看 runs（运行记录）列表是否能正常加载和展示；4. 确认运行记录列表页面能正确显示已有的运行数据，包括 ciBuildId、运行状态等信息。始终在浏览器内操作，禁止打开 Terminal 或其他应用程序。如果在浏览器中找不到目标功能，直接报告 unclear。",
  "expected_result_zh": "Dashboard 首页能正常加载，进入项目后能看到对应的运行记录列表，运行数据（包括 ciBuildId 等）能正确展示，不会出现在有数据的情况下显示空列表的情况。",
  "max_steps": 80,
  "timeout_minutes": 15,
  "repo_size_kb": 5905
}