{
  "app_name": "Svelte Sonner",
  "buggy_commit": "3044099cac",
  "deploy_commands": [
    "git clone https://github.com/wobsoriano/svelte-sonner.git svelte-sonner-57",
    "cd svelte-sonner-57",
    "git checkout 3044099cac",
    "npm install",
    "npm run dev"
  ],
  "deploy_verify": "curl -s http://localhost:5173 | grep -q '<'",
  "dev_url": "http://localhost:5173",
  "expected_result_zh": "Toast 通知中的 action 按钮应保持正常尺寸，不会因为文本内容过长而被压缩/收缩，按钮文字完整显示且布局正常。",
  "fix_commit": "4478323166",
  "framework": "svelte",
  "repo": "wobsoriano/svelte-sonner",
  "repo_size_kb": 578,
  "task_id": "svelte-sonner-pr57",
  "test_description_zh": "在页面中触发一个包含较长文本内容和 action 按钮的 toast 通知，观察 action 按钮的显示状态和尺寸是否正常。",
  "test_page": "/",
  "pr_number": 57,
  "timeout_minutes": 10,
  "issue_number": 57,
  "max_steps": 80
}