{
  "app_name": "Svelte Repl",
  "buggy_commit": "13d88791cc",
  "deploy_commands": [
    "git clone https://github.com/sveltejs/svelte-repl.git svelte-repl-59",
    "cd svelte-repl-59",
    "git checkout 13d88791cc",
    "npm install",
    "npm run dev"
  ],
  "deploy_verify": "curl -s http://localhost:5173 | grep -q '<'",
  "dev_url": "http://localhost:5173",
  "expected_result_zh": "REPL 页面在 Firefox 中正常加载，编辑器和输出面板区域支持正常滚动，浏览器控制台不出现与 overflow scroll 相关的警告信息，页面布局无异常。",
  "fix_commit": "c82639af85",
  "framework": "svelte",
  "repo": "sveltejs/svelte-repl",
  "repo_size_kb": 725,
  "task_id": "svelte-repl-pr59",
  "test_description_zh": "在 Firefox 浏览器中打开 Svelte REPL 页面，观察代码编辑器和输出面板区域的滚动行为，检查浏览器控制台是否有关于 overflow scroll 的警告信息，并验证面板内容在溢出时能否正常滚动。",
  "test_page": "/",
  "pr_number": 59,
  "timeout_minutes": 10,
  "issue_number": 59,
  "max_steps": 80
}