{
  "app_name": "Tensei",
  "buggy_commit": "0eb5b4fb08",
  "deploy_commands": [
    "git clone https://github.com/tenseijs/tensei.git tensei-246",
    "cd tensei-246",
    "git checkout 0eb5b4fb08",
    "npm install",
    "npm run dev"
  ],
  "deploy_verify": "curl -s http://localhost:3000 | grep -q '<'",
  "dev_url": "http://localhost:3000",
  "expected_result_zh": "点击「创建角色」按钮后，新创建的角色应立即自动出现在角色列表表格中，无需手动刷新页面。",
  "fix_commit": "b00dd5f0a3",
  "framework": "react",
  "repo": "tenseijs/tensei",
  "repo_size_kb": 18111,
  "task_id": "tensei-pr246",
  "test_description_zh": "在管理后台进入角色管理页面，填写新角色信息后点击「创建角色」按钮，观察角色列表表格是否自动更新显示新创建的角色。",
  "test_page": "/",
  "pr_number": 246,
  "timeout_minutes": 10,
  "issue_number": 246,
  "max_steps": 80
}