{
  "app_name": "Tiny Editor",
  "buggy_commit": "e9b8d04cc2",
  "deploy_commands": [
    "git clone https://github.com/opentiny/tiny-editor.git tiny-editor-201",
    "cd tiny-editor-201",
    "git checkout e9b8d04cc2",
    "npm install",
    "npm run dev"
  ],
  "deploy_verify": "curl -s http://localhost:5173 | grep -q '<'",
  "dev_url": "http://localhost:5173",
  "expected_result_zh": "从【工具栏提示】demo 切换到其他 demo 时，页面应正常切换并渲染新的 demo 内容，浏览器控制台不应出现报错信息。",
  "fix_commit": "6a1ad7297b",
  "framework": "vue",
  "repo": "opentiny/tiny-editor",
  "repo_size_kb": 3708,
  "task_id": "tiny-editor-201",
  "test_description_zh": "本地启动项目后，在 demo 列表中先切换到【工具栏提示】demo，等待其加载完成后，再点击切换到其他任意 demo，观察页面是否能正常切换以及浏览器控制台是否有报错。",
  "test_page": "/",
  "pr_number": 202,
  "timeout_minutes": 10,
  "issue_number": 201,
  "max_steps": 80
}