{
  "app_name": "Turnstile",
  "buggy_commit": "0c58893560",
  "deploy_commands": [
    "git clone https://github.com/nuxt-modules/turnstile.git turnstile-342",
    "cd turnstile-342",
    "git checkout 0c58893560",
    "npm install",
    "npm run dev"
  ],
  "deploy_verify": "curl -s http://localhost:3000 | grep -q '<'",
  "dev_url": "http://localhost:3000",
  "expected_result_zh": "页面过渡后 Turnstile 组件应正常渲染显示验证挑战，不应出现 'Invalid type for parameter container' 错误，组件容器元素应正确初始化。",
  "fix_commit": "59ab2c4600",
  "framework": "nuxt",
  "repo": "nuxt-modules/turnstile",
  "repo_size_kb": 4487,
  "task_id": "turnstile-342",
  "test_description_zh": "在 Nuxt 应用中，配置两个页面分别包含 Cloudflare Turnstile 组件（例如 login 页面和另一个页面）。从一个包含 Turnstile 的页面通过客户端路由导航到另一个包含 Turnstile 的页面，观察页面过渡后 Turnstile 组件是否正常渲染，控制台是否出现错误。",
  "test_page": "/",
  "pr_number": 344,
  "timeout_minutes": 10,
  "issue_number": 342,
  "max_steps": 80
}