{
  "app_name": "Twake Drive",
  "buggy_commit": "3e01e5646e",
  "deploy_commands": [
    "git clone https://github.com/linagora/twake-drive.git twake-drive-3768",
    "cd twake-drive-3768",
    "git checkout 3e01e5646e",
    "npm install",
    "npm run dev"
  ],
  "deploy_verify": "curl -s http://localhost:3000 | grep -q '<'",
  "dev_url": "http://localhost:3000",
  "expected_result_zh": "当矩形选择框缩小时，不再处于矩形选择区域内的项目应自动取消选中状态，只有当前仍在矩形选择框内的项目保持选中高亮，选中集合应实时随矩形大小变化而更新。",
  "fix_commit": "9a9c977654",
  "framework": "react",
  "repo": "linagora/twake-drive",
  "repo_size_kb": 615126,
  "task_id": "twake-drive-pr3768",
  "test_description_zh": "在文件列表页面中，使用鼠标拖拽绘制矩形选择框选中多个文件/文件夹项目，然后在不松开鼠标的情况下缩小矩形选择框的范围，观察之前被框选但现在不在矩形范围内的项目是否仍处于选中状态。",
  "test_page": "/",
  "pr_number": 3768,
  "timeout_minutes": 10,
  "issue_number": 3768,
  "max_steps": 80
}