{
  "task_id": "typehero-1510",
  "repo": "typehero/typehero",
  "issue_number": 1510,
  "pr_number": 1514,
  "buggy_commit": "92e775a1e6",
  "fix_commit": "ab1b214989",
  "framework": "unknown",
  "deploy_commands": [
    "git clone https://github.com/typehero/typehero.git",
    "cd typehero",
    "git checkout 92e775a1e6",
    "pnpm install --no-frozen-lockfile",
    "npm run dev"
  ],
  "deploy_verify": "curl -s http://localhost:3000 | grep -q '<'",
  "dev_url": "http://localhost:3000",
  "test_page": "/",
  "app_name": "typehero",
  "test_description_zh": "测试 TypeHero 主页的文本换行显示是否正常。具体步骤：1. 打开主页（/）；2. 向下滚动页面，找到社区贡献者相关的区域，该区域包含类似'TypeHero is free, open-source, and built by developers just like you'的文字；3. 检查该段文字是否正确换行显示，而不是在文本中出现字面的'\\n'字符；4. 继续向下滚动到页脚区域，检查包含'Built with'和'Trash Devs'相关文字的区域，确认文本换行正常显示；5. 同时检查包含'Interested in the future of the platform'相关文字的区域，确认换行显示正常。所有多行文本段落应当在适当位置自然换行，不应出现字面的'\\n'文本。始终在浏览器内操作，禁止打开 Terminal 或其他应用程序。如果在浏览器中找不到目标功能，直接报告 unclear。",
  "expected_result_zh": "主页和页脚区域的所有多行文本应正确换行显示，不应在页面上看到字面的'\\n'字符串，文本应在预期位置自然分行呈现。",
  "max_steps": 80,
  "timeout_minutes": 15,
  "repo_size_kb": 104447
}
