{
  "app_name": "Unovis",
  "buggy_commit": "42cbc45183",
  "deploy_commands": [
    "git clone https://github.com/f5/unovis.git unovis-282",
    "cd unovis-282",
    "git checkout 42cbc45183",
    "npm install",
    "npm run dev"
  ],
  "deploy_verify": "curl -s http://localhost:3000 | grep -q '<'",
  "dev_url": "http://localhost:3000",
  "expected_result_zh": "Gallery 页面中所有示例图表均能正确渲染，图表元素完整显示，无空白区域、缺失元素、报错或布局错乱等问题。",
  "fix_commit": "3de0f3077f",
  "framework": "react",
  "repo": "f5/unovis",
  "repo_size_kb": 36038,
  "task_id": "unovis-282",
  "test_description_zh": "访问 Unovis 官方网站的 Gallery（画廊）页面，浏览所有画廊示例，检查每个示例图表是否正常渲染显示，包括图表元素、布局和交互是否完整无误。",
  "test_page": "/",
  "pr_number": 283,
  "timeout_minutes": 10,
  "issue_number": 282,
  "max_steps": 80
}