{
  "app_name": "Vben3",
  "buggy_commit": "7743541a0c",
  "deploy_commands": [
    "git clone https://github.com/vbenjs/vben3.git vben3-209",
    "cd vben3-209",
    "git checkout 7743541a0c",
    "npm install",
    "npm run dev"
  ],
  "deploy_verify": "curl -s http://localhost:5173 | grep -q '<'",
  "dev_url": "http://localhost:5173",
  "expected_result_zh": "左侧菜单在混合模式下展开时，菜单弹出面板应显示在页面所有内容的最顶层（最高 z-index），不会被页面主体区域的表格或其他内容遮挡覆盖。",
  "fix_commit": "71c3734d9d",
  "framework": "vue",
  "repo": "vbenjs/vben3",
  "repo_size_kb": 7604,
  "task_id": "vben3-209",
  "test_description_zh": "1. 进入应用后，打开系统设置，选择'左侧菜单混合模式'作为导航模式。\n2. 在设置中确认'固定展开菜单'选项处于关闭状态（默认关闭）。\n3. 导航到树形表格页面（或任意含有较宽内容/表格的页面）。\n4. 将鼠标悬停到左侧折叠的菜单上，使其展开弹出菜单面板。\n5. 观察展开的菜单面板与页面主体内容区域的层级关系。",
  "test_page": "/",
  "pr_number": 230,
  "timeout_minutes": 10,
  "issue_number": 209,
  "max_steps": 80
}