{
  "app_name": "Vulcan",
  "buggy_commit": "4a4ca0f45a",
  "deploy_commands": [
    "git clone https://github.com/VulcanJS/Vulcan.git Vulcan-2660",
    "cd Vulcan-2660",
    "git checkout 4a4ca0f45a",
    "npm install",
    "npm run dev"
  ],
  "deploy_verify": "curl -s http://localhost:3000 | grep -q '<'",
  "dev_url": "http://localhost:3000",
  "expected_result_zh": "邮箱验证完成后，页面上应正确显示当前已验证用户的登录状态，用户信息（如用户名、头像等）应即时更新并与服务端保持同步，无需手动刷新页面。",
  "fix_commit": "3c360836fd",
  "framework": "react",
  "repo": "VulcanJS/Vulcan",
  "repo_size_kb": 21037,
  "task_id": "Vulcan-pr2660",
  "test_description_zh": "通过邮箱验证链接访问 VerifyEmail 页面，完成邮箱验证流程后，观察页面上当前用户的登录状态和用户信息是否正确同步显示。",
  "test_page": "/",
  "pr_number": 2660,
  "timeout_minutes": 10,
  "issue_number": 2660,
  "max_steps": 80
}