{
  "app_name": "Wuffle",
  "buggy_commit": "b1f9991f1d",
  "deploy_commands": [
    "git clone https://github.com/nikku/wuffle.git wuffle-90",
    "cd wuffle-90",
    "git checkout b1f9991f1d",
    "npm install",
    "npm run dev"
  ],
  "deploy_verify": "curl -s http://localhost:5173 | grep -q '<'",
  "dev_url": "http://localhost:5173",
  "expected_result_zh": "被转移的 issue 在看板中只显示一次（转移后的新位置），不会出现重复显示两条相同 issue 的情况。",
  "fix_commit": "a98ad1b571",
  "framework": "preact",
  "repo": "nikku/wuffle",
  "repo_size_kb": 9740,
  "task_id": "wuffle-90",
  "test_description_zh": "在看板中，将一个 issue 从一个仓库转移（transfer）到另一个仓库后，刷新 Wuffle 看板页面，观察该 issue 在面板中的显示情况。",
  "test_page": "/",
  "pr_number": 184,
  "timeout_minutes": 10,
  "issue_number": 90,
  "max_steps": 80
}