{
  "app_name": "Xpert",
  "buggy_commit": "610832bd7d",
  "deploy_commands": [
    "git clone https://github.com/xpert-ai/xpert.git xpert-142",
    "cd xpert-142",
    "git checkout 610832bd7d",
    "npm install",
    "npm run dev"
  ],
  "deploy_verify": "curl -s http://localhost:4200 | grep -q '<'",
  "dev_url": "http://localhost:4200",
  "expected_result_zh": "拖拽图片到上传区域后，图片应成功上传并在页面上正确显示预览，基本信息中的图片字段应更新为新上传的图片。",
  "fix_commit": "f5b2ac794a",
  "framework": "angular",
  "repo": "xpert-ai/xpert",
  "repo_size_kb": 61791,
  "task_id": "xpert-142",
  "test_description_zh": "进入基本信息编辑页面，尝试通过拖拽方式上传图片到指定区域，观察图片是否成功上传并显示预览。",
  "test_page": "/",
  "pr_number": 143,
  "timeout_minutes": 10,
  "issue_number": 142,
  "max_steps": 80
}