{
  "app_name": "Zardui",
  "buggy_commit": "c850ab1b46",
  "deploy_commands": [
    "git clone https://github.com/zard-ui/zardui.git zardui-451",
    "cd zardui-451",
    "git checkout c850ab1b46",
    "npm install",
    "npm run dev"
  ],
  "deploy_verify": "curl -s http://localhost:4200 | grep -q '<'",
  "dev_url": "http://localhost:4200",
  "expected_result_zh": "鼠标点击树节点时，(zNodeClick) 事件应正常触发，回调函数接收到对应的节点数据。树节点之间的间距应合理、一致，无异常的空白间隔或元素重叠问题。",
  "fix_commit": "0a81eb88d6",
  "framework": "angular",
  "repo": "zard-ui/zardui",
  "repo_size_kb": 14937,
  "task_id": "zardui-451",
  "test_description_zh": "在页面上渲染一个 z-tree 组件，绑定 (zNodeClick) 事件处理器。用鼠标点击树节点，观察 (zNodeClick) 事件是否被触发并正确回调。同时检查树节点之间的间距是否正常显示，无多余空白或重叠。",
  "test_page": "/",
  "pr_number": 452,
  "timeout_minutes": 10,
  "issue_number": 451,
  "max_steps": 80
}