{
  "task_id": "emoji-mart-327",
  "repo": "missive/emoji-mart",
  "worker": "worker-03",
  "status": "completed",
  "sess_id": "sess-20260419015631-18ce125d432046b0a2dc87d8249b66cd",
  "expected_result_used": true,
  "duration_seconds": 312,
  "timestamp": "2026-04-19T02:02:00+08:00",
  "mano_cua": {
    "status": "COMPLETED",
    "total_steps": 32,
    "last_action": "DONE",
    "result": "abnormal",
    "result_summary": "搜索'family'出现重复emoji：同一个👪以'Family'和'Man Woman Boy'两个名称重复显示，共享相同shortcodes(:family:和:man-woman-boy:)。Console无duplicate key警告但有Forced reflow性能违规。两轮测试结果一致。",
    "last_reasoning": "搜索fam/family时搜索结果始终显示2个外观相同的emoji，tooltip确认为同一emoji的两个不同名称条目（Family vs Man Woman Boy），shortcodes完全相同。Console未出现React duplicate key警告，仅有Forced reflow性能违规和无关的Shared Storage API废弃警告。"
  }
}
