{
  "task_id": "mui-tiptap-pr418",
  "repo": "sjdemartini/mui-tiptap",
  "worker": "worker-03",
  "status": "completed",
  "sess_id": "sess-20260423232636-846cc20840c54fc1be9759d847b437fc",
  "expected_result_used": true,
  "duration_seconds": 420,
  "timestamp": "2026-04-23T23:35:00+08:00",
  "mano_cua": {
    "status": "COMPLETED",
    "total_steps": 32,
    "last_action": "DONE",
    "result": "unclear",
    "result_summary": "未在页面中找到目标功能入口。AppBar在当前页面(localhost:5173)中不可见，mano-cua任务面板遮挡了AppBar右侧区域，随后AppBar完全消失且刷新页面后仍不恢复。无法观察View in a dialog按钮的文本颜色对比度",
    "last_reasoning": "多次尝试（刷新、重新加载URL、滚动到顶部）后AppBar始终不可见。页面工具栏直接显示在Chrome地址栏下方，没有深蓝色AppBar空间。View in a dialog按钮无法被找到。"
  }
}
