{
  "task_id": "svelte-typeahead-56",
  "repo": "metonym/svelte-typeahead",
  "worker": "worker-03",
  "status": "completed",
  "sess_id": "sess-20260417013413-fb76985f4a484b0d9c9ae90c8a630b04",
  "expected_result_used": true,
  "duration_seconds": 180,
  "timestamp": "2026-04-17T01:37:00+08:00",
  "mano_cua": {
    "status": "COMPLETED",
    "total_steps": 15,
    "last_action": "DONE",
    "result": "normal",
    "result_summary": "autoselect + disabled 交互正常。搜索 north 时第一个结果 North Carolina（禁用）被跳过，autoselect 高亮到 North Dakota（第一个非禁用项）。搜索 ca 时第一个结果 California（非禁用）被正确高亮。禁用项灰色文字无高亮背景。",
    "last_reasoning": "测试场景1: 搜索 ca 时 California（非禁用）被正确高亮。测试场景2: 搜索 north 时 North Carolina（禁用）被跳过，North Dakota（非禁用）被高亮。autoselect + disabled 交互逻辑工作正常。"
  }
}
