{
  "task_id": "CodeFlask-113",
  "repo": "kazzkiq/CodeFlask",
  "worker": "worker-fabrice",
  "status": "completed",
  "sess_id": "sess-20260428080907-5e9561ebb4e141f78cd16646e5c89ba7",
  "expected_result_used": true,
  "duration_seconds": 180,
  "timestamp": "2026-04-28T08:12:00+08:00",
  "mano_cua": {
    "status": "COMPLETED",
    "total_steps": 14,
    "last_action": "DONE",
    "result": "unclear",
    "result_summary": "页面编辑器配置了 lineNumbers:true 但未配置 readonly:true，无法测试只读模式下 Enter 键行高变化的 bug。mano-cua 查看了页面源码确认仅有一个编辑器且无 readonly 配置，其他路由 /readonly /test 均 404。",
    "last_reasoning": "页面 localhost:3000 仅有一个 CodeFlask 编辑器，配置为 lineNumbers:true 但无 readonly:true。点击编辑器后出现光标，确认可编辑。任务要求 readonly:true 的编辑器不存在于当前页面。"
  }
}
