{
  "task_id": "CodeFlask-pr25",
  "repo": "kazzkiq/CodeFlask",
  "worker": "worker-fabrice",
  "status": "completed",
  "sess_id": "sess-20260428092522-e96c37086215454ea4cf8f672eec3377",
  "expected_result_used": true,
  "duration_seconds": 600,
  "timestamp": "2026-04-28T09:35:00+08:00",
  "mano_cua": {
    "status": "COMPLETED",
    "total_steps": 43,
    "last_action": "DONE",
    "result": "abnormal",
    "result_summary": "桌面 Chrome 测试：输入 20 行代码后滚动流畅无回弹，textarea 文字透明无重叠显示，但文本光标（caret）始终不可见——点击、键盘导航均无法看到闪烁竖线光标。可能原因：textarea 的 caret-color 设为 transparent。注：iOS 特有的滚动回弹/延迟在桌面 Chrome 无法复现。",
    "last_reasoning": "测试完成。滚动正常，文本显示无重叠，但光标始终不可见（caret-color: transparent），这是 iOS 滚动修复 PR 的副作用——为解决 iOS 滚动问题将 textarea 文字设为透明，导致光标也不可见。"
  }
}
